hpsandbox/Chain.py
hpsandbox/Config.py
hpsandbox/Monty.py
hpsandbox/Replica.py
hpsandbox/Trajectory.py
hpsandbox/__init__.py
hpsandbox-1.0.0b0.dist-info/LICENSE
hpsandbox-1.0.0b0.dist-info/METADATA
hpsandbox-1.0.0b0.dist-info/WHEEL
hpsandbox-1.0.0b0.dist-info/top_level.txt
hpsandbox-1.0.0b0.dist-info/RECORD
