Metadata-Version: 2.1
Name: hpsandbox
Version: 1.0.0b0
Summary: Python package to explore the 2D HP model of Chan and Dill.
Home-page: https://github.com/vvoelz/HPSandbox
Author: Vincent Voelz
Author-email: vvoelz@gmail.com
Classifier: Programming Language :: Python :: 3
Classifier: License :: OSI Approved :: MIT License
Classifier: Operating System :: OS Independent
License-File: LICENSE
Requires-Dist: numpy
